{
  "info": {
    "name": "Expense Tracker API",
    "description": "API collection for Expense Tracker application",
    "schema": "https://schema.getpostman.com/json/collection/v2.1.0/collection.json"
  },
  "item": [
    {
      "name": "Health Check",
      "request": {
        "method": "GET",
        "header": [],
        "url": {
          "raw": "{{baseUrl}}/api/health",
          "host": ["{{baseUrl}}"],
          "path": ["api", "health"]
        }
      }
    },
    {
      "name": "Categories",
      "item": [
        {
          "name": "Get All Categories",
          "request": {
            "method": "GET",
            "header": [],
            "url": {
              "raw": "{{baseUrl}}/api/categories",
              "host": ["{{baseUrl}}"],
              "path": ["api", "categories"]
            }
          }
        },
        {
          "name": "Get Category by ID",
          "request": {
            "method": "GET",
            "header": [],
            "url": {
              "raw": "{{baseUrl}}/api/categories/:id",
              "host": ["{{baseUrl}}"],
              "path": ["api", "categories", ":id"],
              "variable": [
                {
                  "key": "id",
                  "value": "category_id_here"
                }
              ]
            }
          }
        },
        {
          "name": "Create Category",
          "request": {
            "method": "POST",
            "header": [
              {
                "key": "Content-Type",
                "value": "application/json"
              }
            ],
            "body": {
              "mode": "raw",
              "raw": "{\n  \"name\": \"Food & Dining\",\n  \"icon\": \"🍕\",\n  \"color\": \"#FF6B6B\"\n}"
            },
            "url": {
              "raw": "{{baseUrl}}/api/categories",
              "host": ["{{baseUrl}}"],
              "path": ["api", "categories"]
            }
          }
        },
        {
          "name": "Update Category",
          "request": {
            "method": "PUT",
            "header": [
              {
                "key": "Content-Type",
                "value": "application/json"
              }
            ],
            "body": {
              "mode": "raw",
              "raw": "{\n  \"name\": \"Food & Dining Updated\",\n  \"icon\": \"🍔\",\n  \"color\": \"#FF8C8C\"\n}"
            },
            "url": {
              "raw": "{{baseUrl}}/api/categories/:id",
              "host": ["{{baseUrl}}"],
              "path": ["api", "categories", ":id"],
              "variable": [
                {
                  "key": "id",
                  "value": "category_id_here"
                }
              ]
            }
          }
        },
        {
          "name": "Delete Category",
          "request": {
            "method": "DELETE",
            "header": [],
            "url": {
              "raw": "{{baseUrl}}/api/categories/:id",
              "host": ["{{baseUrl}}"],
              "path": ["api", "categories", ":id"],
              "variable": [
                {
                  "key": "id",
                  "value": "category_id_here"
                }
              ]
            }
          }
        }
      ]
    },
    {
      "name": "Expenses",
      "item": [
        {
          "name": "Get All Expenses",
          "request": {
            "method": "GET",
            "header": [],
            "url": {
              "raw": "{{baseUrl}}/api/expenses?page=1&limit=50",
              "host": ["{{baseUrl}}"],
              "path": ["api", "expenses"],
              "query": [
                {
                  "key": "page",
                  "value": "1"
                },
                {
                  "key": "limit",
                  "value": "50"
                }
              ]
            }
          }
        },
        {
          "name": "Get Expenses with Filters",
          "request": {
            "method": "GET",
            "header": [],
            "url": {
              "raw": "{{baseUrl}}/api/expenses?categoryId=category_id&startDate=2024-02-01&endDate=2024-02-29",
              "host": ["{{baseUrl}}"],
              "path": ["api", "expenses"],
              "query": [
                {
                  "key": "categoryId",
                  "value": "category_id"
                },
                {
                  "key": "startDate",
                  "value": "2024-02-01"
                },
                {
                  "key": "endDate",
                  "value": "2024-02-29"
                }
              ]
            }
          }
        },
        {
          "name": "Get Expense by ID",
          "request": {
            "method": "GET",
            "header": [],
            "url": {
              "raw": "{{baseUrl}}/api/expenses/:id",
              "host": ["{{baseUrl}}"],
              "path": ["api", "expenses", ":id"],
              "variable": [
                {
                  "key": "id",
                  "value": "expense_id_here"
                }
              ]
            }
          }
        },
        {
          "name": "Create Expense",
          "request": {
            "method": "POST",
            "header": [
              {
                "key": "Content-Type",
                "value": "application/json"
              }
            ],
            "body": {
              "mode": "raw",
              "raw": "{\n  \"title\": \"Coffee\",\n  \"amount\": 4.50,\n  \"date\": \"2024-02-08T10:30:00Z\",\n  \"categoryId\": \"category_id_here\",\n  \"notes\": \"Morning coffee\"\n}"
            },
            "url": {
              "raw": "{{baseUrl}}/api/expenses",
              "host": ["{{baseUrl}}"],
              "path": ["api", "expenses"]
            }
          }
        },
        {
          "name": "Update Expense",
          "request": {
            "method": "PUT",
            "header": [
              {
                "key": "Content-Type",
                "value": "application/json"
              }
            ],
            "body": {
              "mode": "raw",
              "raw": "{\n  \"title\": \"Coffee Updated\",\n  \"amount\": 5.00,\n  \"date\": \"2024-02-08T10:30:00Z\",\n  \"categoryId\": \"category_id_here\",\n  \"notes\": \"Updated morning coffee\"\n}"
            },
            "url": {
              "raw": "{{baseUrl}}/api/expenses/:id",
              "host": ["{{baseUrl}}"],
              "path": ["api", "expenses", ":id"],
              "variable": [
                {
                  "key": "id",
                  "value": "expense_id_here"
                }
              ]
            }
          }
        },
        {
          "name": "Delete Expense",
          "request": {
            "method": "DELETE",
            "header": [],
            "url": {
              "raw": "{{baseUrl}}/api/expenses/:id",
              "host": ["{{baseUrl}}"],
              "path": ["api", "expenses", ":id"],
              "variable": [
                {
                  "key": "id",
                  "value": "expense_id_here"
                }
              ]
            }
          }
        }
      ]
    },
    {
      "name": "Analytics",
      "item": [
        {
          "name": "Get Spending Analytics",
          "request": {
            "method": "GET",
            "header": [],
            "url": {
              "raw": "{{baseUrl}}/api/analytics/spending?startDate=2024-02-01&endDate=2024-02-29",
              "host": ["{{baseUrl}}"],
              "path": ["api", "analytics", "spending"],
              "query": [
                {
                  "key": "startDate",
                  "value": "2024-02-01"
                },
                {
                  "key": "endDate",
                  "value": "2024-02-29"
                }
              ]
            }
          }
        },
        {
          "name": "Get Summary Analytics",
          "request": {
            "method": "GET",
            "header": [],
            "url": {
              "raw": "{{baseUrl}}/api/analytics/summary",
              "host": ["{{baseUrl}}"],
              "path": ["api", "analytics", "summary"]
            }
          }
        }
      ]
    }
  ],
  "variable": [
    {
      "key": "baseUrl",
      "value": "http://localhost:3001"
    }
  ]
}
